autogradercpp
