Metadata-Version: 2.1
Name: autogradercpp
Version: 0.1.4
Summary: An autograder library for evaluating C++ programs.
Author: Abhijat Bharadwaj (Keymii)
Author-email: bharadwaj.abhijat@yahoo.com
Project-URL: GitHub, https://github.com/Keymii/autograder-for-cpp
Classifier: Programming Language :: Python :: 3
Classifier: License :: OSI Approved :: MIT License
Classifier: Operating System :: OS Independent
License-File: LICENSE
